{"CmXX07S+0fz/kbcawDcrZw==":"-mg-9599web-2000x1333.jpg","6Med3r5slFKH83xlPXIE6Q==":"bridge-2000x1333.jpg","2oJBuhMnKP2fXztz7skqtA==":"%D0%9C%D0%BE%D0%BD%D1%82%D0%B0%D0%B6%D0%BD%D0%B0%D1%8F%20%D0%BE%D0%B1%D0%BB%D0%B0%D1%81%D1%82%D1%8C%201xxxhdpi-2000x509.png","tEcgUhWeEKnOjHANeUG7+w==":"-1-600x600.jpg","J6VH/k6Xac4kuCIzJZn3lA==":"-1-1-600x600.jpg","g+aLXOJ0+0FYIEDS5OyWLQ==":"briga-600x600.jpg","wsR+7TPzIisnGvCIzsfZgA==":"img4-600x574.png","dTSUTo4MmzHIZTtNfeSikQ==":"-1-265x265.jpg","nTLvK5IwLMOMnAo4JFsMUw==":"img-2510web-2000x1333.jpg","h9N2CX8CATTMC1DdBL0bxg==":"1-128x128.jpg","JEMpWmFfBTeY4v7K8Ohneg==":"growth-a9042d36e92dbf63d04cf902a35dd6a533b6ae20069537bdd457c46e07894078-600x416.jpg","VET714+1M/p3tEvS5qxjVg==":"img-2510web-1-2000x1333.jpg","19m/V/tvokEbTfTeikpbfg==":"_mg-2000x1333.jpg","fcX9b/8ZQQUa35k1TIlXuw==":"%D0%91%D0%B5%D0%B7%D1%8B%D0%BC%D1%8F%D0%BD%D0%BD%D1%8B%D0%B9-1400x370.png","elxUwLcp4cM578Eww9rsMg==":"%D1%8D%D0%BC%D0%B1%D0%BB%D0%B5%D0%BC%D0%B0-265x176.png","wddw28E107CgxjPqOE/d/A==":"unj-1400x356.png","9B/E0ARGVEomNdcUU8solg==":"-_1_~1-1400x1400.jpg","RheErN4NFev2tRPDJPXX/w==":"%D0%91%D0%B0%D0%B7%D0%B8%D0%BB%D0%B5%D0%B2%D1%81%D0%BA%D0%B8%D0%B9-1400x1400.png","16tqZl0OX/RSFDsYCcXMXw==":"%D0%91%D0%B0%D0%B7%D0%B8%D0%BB%D0%B5%D0%B2%D1%81%D0%BA%D0%B8%D0%B9_300%202-1400x2100.jpg","IhvZvBs3lug4lyBwwmetWg==":"logo_ge-1400x261.png","he21QCAW4hCiV8ucxSC50w==":"team-600x600.jpg","XGvAgaymIcaZLov0NcmzVw==":"team-1-600x600.jpg","qQXm+7PnymutqH8UAE19dQ==":"mbr-600x361.jpg","DjqAB7S1/c+8L/Pb1/nPuQ==":"mbr-600x424.jpg","7PxH8llU7nQ6zlCoWb+usw==":"mbr-600x400.jpg","UV4l08fi/oPYEGDFkIul7Q==":"team-1400x1400.jpg","4fXBYjtKGM3VxkGhf1jgHg==":"img-600x399.jpg","awQaZ6J1Zus+XQKr43VtVw==":"unnamed-600x359.jpg","8cgv31BNiDXttilzvvGJFg==":"1--600x329.jpg","f/r8JSk8/rBxBbUQ/jbKWw==":"1-600x399.jpg","lo3qf0rzyRuE/aezHDtRLg==":"kkz-600x400.jpg","/eqKkrMKGjRfKrOaFnMdPA==":"%D0%A1%D0%BD%D0%B8%D0%BC%D0%BE%D0%BA%20%D1%8D%D0%BA%D1%80%D0%B0%D0%BD%D0%B0%202017-03-09%20%D0%B2%2016-1400x1063.png","ksnCusvLNLZpxbLpVZcG+A==":"%D0%A1%D0%BD%D0%B8%D0%BC%D0%BE%D0%BA%20%D1%8D%D0%BA%D1%80%D0%B0%D0%BD%D0%B0%202017-03-09%20%D0%B2%2016-1400x1062.png","dbglraTeYQTY65JEh2sAJw==":"%D0%A1%D0%BD%D0%B8%D0%BC%D0%BE%D0%BA%20%D1%8D%D0%BA%D1%80%D0%B0%D0%BD%D0%B0%202017-03-09%20%D0%B2%2016-1400x1067.png","DdyCF1qcptH+sHXSo++CwQ==":"%D0%A1%D0%BD%D0%B8%D0%BC%D0%BE%D0%BA%20%D1%8D%D0%BA%D1%80%D0%B0%D0%BD%D0%B0%202017-03-09%20%D0%B2%2017-1400x886.png","bVcDTHWrhYva5kT3Wp1+rA==":"%D1%8D%D0%BC%D0%B1%D0%BB%D0%B5%D0%BC%D0%B0-192x128.png"}